Metadata-Version: 2.1
Name: modulito
Version: 0.1
Summary: 100 intento de crear modulo
Author: LuchD
Classifier: Programming Language :: Python :: 3
Classifier: License :: OSI Approved :: MIT License
Classifier: Operating System :: OS Independent
